.gitignore
LICENSE
MANIFEST.in
README.md
pyproject.toml
setup.cfg
setup.py
tox.ini
src/grq/__init__.py
src/grq.egg-info/PKG-INFO
src/grq.egg-info/SOURCES.txt
src/grq.egg-info/dependency_links.txt
src/grq.egg-info/entry_points.txt
src/grq.egg-info/not-zip-safe
src/grq.egg-info/requires.txt
src/grq.egg-info/top_level.txt